<?xml version="1.0" encoding="utf-8" ?>
<dwsync>
<file name="Roboto-Bold.woff2" server="bankucolombia.com/public_html/" local="131426232880000000" remote="131453177400000000" Dst="0" />
<file name="Roboto-Bold.woff" server="bankucolombia.com/public_html/" local="131426232880000000" remote="131453177400000000" Dst="0" />
<file name="Roboto-Light.woff" server="bankucolombia.com/public_html/" local="131426232880000000" remote="131453177400000000" Dst="0" />
<file name="Roboto-Light.woff2" server="bankucolombia.com/public_html/" local="131426232880000000" remote="131453177400000000" Dst="0" />
<file name="Roboto-Medium.woff2" server="bankucolombia.com/public_html/" local="131426232880000000" remote="131453177400000000" Dst="0" />
<file name="Roboto-Medium.woff" server="bankucolombia.com/public_html/" local="131426232880000000" remote="131453177400000000" Dst="0" />
<file name="Roboto-Regular.woff" server="bankucolombia.com/public_html/" local="131426232880000000" remote="131453177400000000" Dst="0" />
<file name="Roboto-Regular.woff2" server="bankucolombia.com/public_html/" local="131426232880000000" remote="131453177400000000" Dst="0" />
<file name="Roboto-Thin.woff" server="bankucolombia.com/public_html/" local="131426232880000000" remote="131453177400000000" Dst="0" />
<file name="Roboto-Thin.woff2" server="bankucolombia.com/public_html/" local="131426232880000000" remote="131453177400000000" Dst="0" />
</dwsync>